hcct/Hachi_filter.py
hcct/__init__.py
hcct/contact.py
hcct/test_for_contact.py
hcct-0.0.3.dist-info/DESCRIPTION.rst
hcct-0.0.3.dist-info/METADATA
hcct-0.0.3.dist-info/RECORD
hcct-0.0.3.dist-info/WHEEL
hcct-0.0.3.dist-info/metadata.json
hcct-0.0.3.dist-info/top_level.txt
